lubepy/__init__.py
lubepy/exceptions.py
lubepy/device/__init__.py
lubepy/device/bearing.py
lubepy/fluid/__init__.py
lubepy/fluid/reynolds.py
lubepy/lube/__init__.py
lubepy/lube/blend.py
lubepy/lube/mixture.py
lubepy/lube/viscosity.py
lubepy/validator/__init__.py
lubepy/validator/core.py
lubepy-1.0a0.dist-info/LICENSE
lubepy-1.0a0.dist-info/METADATA
lubepy-1.0a0.dist-info/WHEEL
lubepy-1.0a0.dist-info/top_level.txt
lubepy-1.0a0.dist-info/RECORD
