Metadata-Version: 2.1
Name: lubepy
Version: 1.0a0
Summary: Lubepy provides a basic set of machinery lubrication calculations.
Home-page: https://github.com/lpozo/lubepy
Author: Leodanis Pozo Ramos
Author-email: lpozor78@gmail.com
License: GNU General Public License, Version 2, June 1991
Keywords: machinery lubrication,oil,grease,lubrication engineering
Platform: linux
Platform: darwin
Classifier: License :: OSI Approved :: GNU General Public License v2 (GPLv2)
Classifier: Programming Language :: Python
Classifier: Programming Language :: Python :: 3
Classifier: Programming Language :: Python :: 3.6
Classifier: Programming Language :: Python :: 3.7
Classifier: Programming Language :: Python :: 3.8
Classifier: Programming Language :: Python :: Implementation :: CPython
Requires-Python: >=3.6
